sccore/__init__.py
sccore/matrix.py
sccore/parse_chemistry.py
sccore/starsolo.py
sccore/utils.py
sccore/chemistry/__init__.py
sccore/chemistry/chemistry_dict.py
sccore/chemistry/AccuraSCOPE_DNA/bc.txt
sccore/chemistry/AccuraSCOPE_RNA_3p/bc.txt
sccore/chemistry/AccuraSCOPE_RNA_5p/bc.txt
sccore/chemistry/GEXSCOPE-V1/bc.txt
sccore/chemistry/GEXSCOPE-V1/linker1.txt
sccore/chemistry/GEXSCOPE-V1/linker2.txt
sccore/chemistry/GEXSCOPE-V2/bc1.txt
sccore/chemistry/GEXSCOPE-V2/bc2.txt
sccore/chemistry/GEXSCOPE-V2/bc3.txt
sccore/chemistry/GEXSCOPE-V2/linker1.txt
sccore/chemistry/GEXSCOPE-V2/linker2.txt
sccore/chemistry/GEXSCOPE-V3/bc1.txt
sccore/chemistry/GEXSCOPE-V3/bc2.txt
sccore/chemistry/GEXSCOPE-V3/bc3.txt
sccore/chemistry/GEXSCOPE-V3/linker1.txt
sccore/chemistry/GEXSCOPE-V3/linker2.txt
sccore/chemistry/bulk_rna-V1/bc.txt
sccore/chemistry/bulk_rna-V2/bc.txt
sccore/chemistry/bulk_rna-V3/bc.txt
sccore/chemistry/bulk_rna-bulk_vdj_match/bc.txt
sccore/chemistry/bulk_vdj/bc.txt
sccore/chemistry/bulk_vdj/linker.txt
sccore/chemistry/flv/bc.txt
sccore/chemistry/flv/linker1.txt
sccore/chemistry/flv/linker2.txt
sccore/chemistry/flv-V2/bc1.txt
sccore/chemistry/flv-V2/bc2.txt
sccore/chemistry/flv-V2/bc3.txt
sccore/chemistry/flv-V2/linker1.txt
sccore/chemistry/flv-V2/linker2.txt
sccore/chemistry/flv-V2/linker3.txt
sccore/chemistry/flv_rna/bc.txt
sccore/chemistry/flv_rna/linker1.txt
sccore/chemistry/flv_rna/linker2.txt
sccore/chemistry/flv_rna-V2/bc1.txt
sccore/chemistry/flv_rna-V2/bc2.txt
sccore/chemistry/flv_rna-V2/bc3.txt
sccore/chemistry/flv_rna-V2/linker1.txt
sccore/chemistry/flv_rna-V2/linker2.txt
sccore/chemistry/flv_rna-V2/linker3.txt
sccore/cli/__init__.py
sccore/cli/add_exogenous_genes.py
sccore/cli/bam2fastq.py
sccore/cli/celespace.py
sccore/cli/citeseq_otsu.py
sccore/cli/cloud_convert.py
sccore/cli/count_umi.py
sccore/cli/create_genome.py
sccore/cli/create_test.py
sccore/cli/create_test_data.py
sccore/cli/delete_file.py
sccore/cli/delete_files.py
sccore/cli/filter_gtf.py
sccore-1.2.2.dist-info/METADATA
sccore-1.2.2.dist-info/WHEEL
sccore-1.2.2.dist-info/entry_points.txt
sccore-1.2.2.dist-info/top_level.txt
sccore-1.2.2.dist-info/RECORD
