Metadata-Version: 2.4
Name: sccore
Version: 1.2.2
Summary: Single Cell core functions
Home-page: https://github.com/singleron-RD/sccore
Author: zhouyiqi
Author-email: zhouyiqi@singleronbio.com
Classifier: Programming Language :: Python :: 3
Classifier: License :: OSI Approved :: MIT License
Classifier: Operating System :: OS Independent
Requires-Python: >=3.10
Requires-Dist: pysam
Requires-Dist: pandas
Requires-Dist: scipy
Dynamic: author
Dynamic: author-email
Dynamic: classifier
Dynamic: description
Dynamic: description-content-type
Dynamic: home-page
Dynamic: requires-dist
Dynamic: requires-python
Dynamic: summary
